range_typed_integers/__init__.py
range_typed_integers/check.py
range_typed_integers/py.typed
range_typed_integers/types.py
range_typed_integers-1.0.0.dist-info/LICENSE
range_typed_integers-1.0.0.dist-info/METADATA
range_typed_integers-1.0.0.dist-info/WHEEL
range_typed_integers-1.0.0.dist-info/top_level.txt
range_typed_integers-1.0.0.dist-info/RECORD
