Metadata-Version: 2.1
Name: range-typed-integers
Version: 1.0.0
Summary: Integer type aliases that specify valid value ranges.
Author-email: Marco 'Capypara' Köpcke <hello@capypara.de>
License: MIT
Project-URL: repository, https://github.com/theCapypara/range-typed-integers
Classifier: Development Status :: 4 - Beta
Classifier: License :: OSI Approved :: MIT License
Classifier: Programming Language :: Python :: 3.8
Classifier: Programming Language :: Python :: 3.9
Classifier: Programming Language :: Python :: 3.10
Classifier: Programming Language :: Python
Requires-Python: >=3.8
License-File: LICENSE
Requires-Dist: typing-extensions (>=3.9) ; python_version < "3.9"
Provides-Extra: test
Requires-Dist: pytest ; extra == 'test'
Requires-Dist: tox ; extra == 'test'
